jumpthegun_precommit_wrapper/__version__.py
jumpthegun_precommit_wrapper/entrypoint.sh
jumpthegun_precommit_wrapper/main.py
jumpthegun_precommit_wrapper-0.0.2.data/data/bin/jtg-pre-commit
jumpthegun_precommit_wrapper-0.0.2.dist-info/METADATA
jumpthegun_precommit_wrapper-0.0.2.dist-info/WHEEL
jumpthegun_precommit_wrapper-0.0.2.dist-info/entry_points.txt
jumpthegun_precommit_wrapper-0.0.2.dist-info/licenses/LICENSE
jumpthegun_precommit_wrapper-0.0.2.dist-info/RECORD
