Metadata-Version: 2.4
Name: jumpthegun-precommit-wrapper
Version: 0.0.2
Summary: A wrapper for pre-commit to launch Python tools via JumpTheGun
Project-URL: Homepage, https://github.com/taleinat/jumpthegun
Author-email: Tal Einat <taleinat@gmail.com>
License: MIT License
License-File: LICENSE
Classifier: Development Status :: 1 - Planning
Classifier: Environment :: Console
Classifier: Intended Audience :: Developers
Classifier: License :: OSI Approved :: Apache Software License
Classifier: Operating System :: MacOS :: MacOS X
Classifier: Operating System :: POSIX :: Linux
Classifier: Programming Language :: Python
Classifier: Programming Language :: Python :: 3 :: Only
Classifier: Programming Language :: Python :: 3.8
Classifier: Programming Language :: Python :: 3.9
Classifier: Programming Language :: Python :: 3.10
Classifier: Programming Language :: Python :: 3.11
Classifier: Programming Language :: Python :: 3.12
Classifier: Programming Language :: Python :: 3.13
Requires-Python: >=3.8
Requires-Dist: jumpthegun
Requires-Dist: pre-commit
